{
    "Date of Birth": "2005-05-15 00:00:00",
    "First Name": "Marron",
    "Middle Name (Optional)": "",
    "Last Name": "Francia",
    "Age": "19",
    "Gender": "Male",
    "Phone Number": "09123143923",
    "Email": "marron@gmail.com",
    "Social Media Links": "marron.francia/facebook.com",
    "Country": "Philippines",
    "State/Province": "Metro Manila",
    "City": "Manila",
    "Street Address": "Padre Noval St.",
    "Postal Code": "1008",
    "Primary Field Specialization": "Internal Medicine",
    "Secondary Field Specialization": "Cardiology",
    "Years of Experience": "12",
    "Your Title (e.g., RN, MD, DO, etc.)": "RN",
    "Affiliated Hospitals/Clinics (Separate entries with commas)": "UST Hospital",
    "License Number": "2310344",
    "Availability": "In-Person Consultation",
    "Rate": "500",
    "Schedule for Consultation *Ex. (7:00 AM - 9:00 PM)": "6:00 AM - 9:00 AM",
    "I agree to the terms and conditions": true,
    "I consent to the collection and use of my health data": false
}